{
	"$schema": "./node_modules/@biomejs/biome/configuration_schema.json",
	"organizeImports": {
		"enabled": true
	},
	"linter": {
		"enabled": true,
		"rules": {
			"recommended": true,
			"nursery": {
				"useSortedClasses": "warn"
			},
			"correctness": {
				"useExhaustiveDependencies": "off"
			}
		}
	},
	"formatter": {
		"enabled": true
	},
	"files": {
		"ignore": [
			"scripts/*.js",
			"src/contracts/*.sol",
			"assets",
			"public",
			".vercel",
			"node_modules",
			"cache",
			".vscode",
			".next",
			"artifacts"
		]
	},
	"javascript": {
		"formatter": {
			"jsxQuoteStyle": "double",
			"quoteProperties": "asNeeded",
			"trailingCommas": "all",
			"semicolons": "asNeeded",
			"arrowParentheses": "always",
			"bracketSpacing": true,
			"bracketSameLine": false,
			"quoteStyle": "single",
			"attributePosition": "auto",
			"lineWidth": 120
		}
	}
}
